kaldi_io/__init__.py
kaldi_io/kaldi_io.py
tests/__init__.py
tests/test_cnet_posteriors.py
tests/test_compressed_feats.py
tests/test_kaldi_io.py
kaldi_io-0.9.8.dist-info/LICENSE
kaldi_io-0.9.8.dist-info/METADATA
kaldi_io-0.9.8.dist-info/WHEEL
kaldi_io-0.9.8.dist-info/top_level.txt
kaldi_io-0.9.8.dist-info/RECORD
