Metadata-Version: 2.1
Name: kaldi-io
Version: 0.9.8
Summary: Glue code connecting Kaldi data and Python.
Home-page: https://github.com/vesis84/kaldi-io-for-python
Author: Karel Vesely
Classifier: Programming Language :: Python :: 3
Classifier: Programming Language :: Python :: 2
Classifier: License :: OSI Approved :: Apache Software License
Classifier: Operating System :: POSIX :: Linux
Classifier: Topic :: Multimedia :: Sound/Audio :: Speech
License-File: LICENSE
Requires-Dist: numpy (>=1.15.3)
